LICENSE
MANIFEST.in
README.md
setup.py
google_cloud_profiler.egg-info/PKG-INFO
google_cloud_profiler.egg-info/SOURCES.txt
google_cloud_profiler.egg-info/dependency_links.txt
google_cloud_profiler.egg-info/requires.txt
google_cloud_profiler.egg-info/top_level.txt
googlecloudprofiler/__init__.py
googlecloudprofiler/__version__.py
googlecloudprofiler/backoff.py
googlecloudprofiler/builder.py
googlecloudprofiler/client.py
googlecloudprofiler/cpu_profiler.py
googlecloudprofiler/profile_pb2.py
googlecloudprofiler/pythonprofiler.py
googlecloudprofiler/src/_profiler.cc
googlecloudprofiler/src/clock.cc
googlecloudprofiler/src/clock.h
googlecloudprofiler/src/log.cc
googlecloudprofiler/src/log.h
googlecloudprofiler/src/populate_frames.cc
googlecloudprofiler/src/populate_frames.h
googlecloudprofiler/src/profiler.cc
googlecloudprofiler/src/profiler.h
googlecloudprofiler/src/stacktraces.cc
googlecloudprofiler/src/stacktraces.h