Metadata-Version: 2.1
Name: google-cloud-profiler
Version: 4.1.0
Summary: Google Cloud Profiler Python Agent
Home-page: https://github.com/GoogleCloudPlatform/cloud-profiler-python
Author: Google LLC
License: Apache License, Version 2.0
Keywords: google cloud profiler
Classifier: Development Status :: 5 - Production/Stable
Classifier: Intended Audience :: Developers
Classifier: License :: OSI Approved :: Apache Software License
Classifier: Programming Language :: Python :: 3.7
Classifier: Programming Language :: Python :: 3.8
Classifier: Programming Language :: Python :: 3.9
Classifier: Programming Language :: Python :: 3.10
Classifier: Programming Language :: Python :: 3.11
License-File: LICENSE
